pygments_shilldb/__init__.py
pygments_shilldb-0.2.dist-info/DESCRIPTION.rst
pygments_shilldb-0.2.dist-info/METADATA
pygments_shilldb-0.2.dist-info/RECORD
pygments_shilldb-0.2.dist-info/WHEEL
pygments_shilldb-0.2.dist-info/entry_points.txt
pygments_shilldb-0.2.dist-info/metadata.json
pygments_shilldb-0.2.dist-info/top_level.txt
