Metadata-Version: 2.0
Name: pygments-shilldb
Version: 0.2
Summary: Pygments lexer for ShillDB.
Home-page: https://github.com/hugomaiavieira/pygments-rspec
Author: Ezra Zigmond
Author-email: UNKNOWN
License: UNKNOWN
Platform: UNKNOWN
Requires-Dist: pygments (>=2.2)
